base_classes/__init__.py
base_classes/loading.py
base_classes/member.py
beam_classes/__init__.py
beam_classes/beam.py
beam_classes/continuousbeam.py
continuousbeam_backend-2023.11.0.dist-info/LICENSE
continuousbeam_backend-2023.11.0.dist-info/METADATA
continuousbeam_backend-2023.11.0.dist-info/WHEEL
continuousbeam_backend-2023.11.0.dist-info/top_level.txt
continuousbeam_backend-2023.11.0.dist-info/RECORD
