Metadata-Version: 2.1
Name: continuousbeam-backend
Version: 2023.11.0
Summary: Structural analysis of continuous beam using stiffness matrix method
Author-email: "Sanjay G. Khirwadkar" <khirwadkar@gmail.com>
License: MIT License
Project-URL: Homepage, https://github.com/khirwadkar/StructInsight_in_Python
Keywords: continuous beam,indeterminate beam,stiffness matrix,structural engineering,structural analysis
Classifier: License :: OSI Approved :: MIT License
Classifier: Programming Language :: Python
Classifier: Programming Language :: Python :: 3
Classifier: Topic :: Scientific/Engineering
Requires-Python: >=3.8
License-File: LICENSE
Requires-Dist: numpy >=1.23
